stac_api_load_testing/cli.py
stac_api_load_testing-0.2.0.dist-info/LICENSE
stac_api_load_testing-0.2.0.dist-info/METADATA
stac_api_load_testing-0.2.0.dist-info/WHEEL
stac_api_load_testing-0.2.0.dist-info/entry_points.txt
stac_api_load_testing-0.2.0.dist-info/top_level.txt
stac_api_load_testing-0.2.0.dist-info/RECORD
