Metadata-Version: 2.1
Name: stac_api_load_testing
Version: 0.2.0
Summary: Load testing for stac compliant apis
Home-page: https://github.com/Healy-Hyperspatial/stac-api-load-testing
Author: Jonathan Healy
Author-email: jonathan.d.healy@gmail.com
License: MIT
Requires-Python: >=3.7
License-File: LICENSE
Requires-Dist: click >=7.1.2
Requires-Dist: locust
Requires-Dist: setuptools
Requires-Dist: Cython
Requires-Dist: bzt
Provides-Extra: test
Requires-Dist: pytest ; extra == 'test'
